LICENSE.md
drf_rfc7807_exceptions/__init__.py
drf_rfc7807_exceptions/apps.py
drf_rfc7807_exceptions/exception_handler.py
drf_rfc7807_exceptions/exceptions.py
drf_rfc7807_exceptions/handlers.py
drf_rfc7807_exceptions/settings.py
drf_rfc7807_exceptions/utils.py
drf_rfc7807_exceptions-0.1.0.dist-info/LICENSE.md
drf_rfc7807_exceptions-0.1.0.dist-info/WHEEL
drf_rfc7807_exceptions-0.1.0.dist-info/METADATA
drf_rfc7807_exceptions-0.1.0.dist-info/RECORD
