Metadata-Version: 2.1
Name: drf-rfc7807-exceptions
Version: 0.1.0
Summary: A library for Django Rest Framework returning consistent and easy-to-parse error messages inspired by RFC7807 guidelines.
Home-page: https://github.com/gripep/drf-rfc7807-exceptions
License: MIT
Keywords: python,django,django rest framework,drf,error handling,errors,exceptions
Author: Gian
Author-email: 30044863+gripep@users.noreply.github.com
Requires-Python: >=3.8.1,<4.0
Classifier: Framework :: Django
Classifier: License :: OSI Approved :: MIT License
Classifier: Operating System :: OS Independent
Classifier: Programming Language :: Python
Classifier: Programming Language :: Python :: 3
Classifier: Programming Language :: Python :: 3.9
Classifier: Programming Language :: Python :: 3.10
Classifier: Programming Language :: Python :: 3.11
Classifier: Programming Language :: Python :: 3.10
Classifier: Programming Language :: Python :: 3.8
Classifier: Programming Language :: Python :: 3.9
Classifier: Topic :: Software Development :: Libraries :: Application Frameworks
Classifier: Topic :: Software Development :: Libraries :: Python Modules
Requires-Dist: Django (>=2.2)
Requires-Dist: djangorestframework (>=3.0)
Project-URL: Documentation, https://github.com/gripep/drf-rfc7807-exceptions/blob/master/README.md
Project-URL: Repository, https://github.com/gripep/drf-rfc7807-exceptions
